{"version":19,"variables":[{"key":"Error_Message","visible":true,"type":"query","version":2,"editable":true,"input":"fetch logs\n| filter outsystems.log.type == \"Error\"\n| sort exception.message asc\n| summarize collectDistinct(exception.message)\n","multiple":true},{"key":"Application","visible":true,"type":"query","version":2,"editable":true,"input":"fetch logs\n| filterOut outsystems.app.name == \"\"\n| sort outsystems.app.name asc\n| summarize collectDistinct(outsystems.app.name)","multiple":true},{"key":"Environment","visible":true,"type":"query","version":2,"editable":true,"input":"fetch logs //, scanLimitGBytes: 500, samplingRatio: 1000\n| fieldsAdd strTenant=toString(deployment.environment)\n| sort strTenant asc\n| summarize collectDistinct(deployment.environment)","multiple":true}],"tiles":{"0":{"title":"","type":"data","query":"fetch logs //, scanLimitGBytes: 500, samplingRatio: 1000\n| filter contains(outsystems.log.type, \"Error\")\n| filter in(exception.message, $Error_Message)\n| filter in(outsystems.app.name, $Application)\n| filter in(deployment.environment, $Environment)\n| fields Timestamp=timestamp, \n  Application=outsystems.app.name, \n  RequestKey=request_key, \n  Message=content, \n  Stacktrace=stack_trace, \n  Host=server_name, \n  Environment=deployment.environment, \n  Tag=tags, \n  SessionId=session_id\n| sort Timestamp desc","visualization":"table","visualizationSettings":{"table":{"lineWrapIds":[["content"]]},"thresholds":[]},"querySettings":{"maxResultRecords":1000,"defaultScanLimitGbytes":500,"maxResultMegaBytes":100,"defaultSamplingRatio":10,"enableSampling":false},"davis":{}},"1":{"type":"markdown","content":"### Error raw data\n> Original Outsystems platform logs. Tabel can be filtered by clicking on items"}},"layouts":{"0":{"x":0,"y":3,"w":24,"h":15},"1":{"x":0,"y":0,"w":24,"h":3}},"importedWithCode":false,"settings":{}}